primecount.cpython-36m-x86_64-linux-gnu.so
primecount-1.0.0.dist-info/METADATA
primecount-1.0.0.dist-info/RECORD
primecount-1.0.0.dist-info/LICENSE
primecount-1.0.0.dist-info/top_level.txt
primecount-1.0.0.dist-info/WHEEL
primecount.libs/libprimecount-ea3c6509.so.6.1
primecount.libs/libprimesieve-c9f10110.so.9.5.0
primecount.libs/libgomp-7c85b1e2.so.1.0.0
